hans/__init__.py
hans/__main__.py
hans/field.py
hans/geometry.py
hans/input.py
hans/integrate.py
hans/material.py
hans/plottools.py
hans/problem.py
hans/stress.py
hans/tools.py
hans/cli/__init__.py
hans/cli/animate1D.py
hans/cli/animate2D.py
hans/cli/generate_roughness.py
hans/cli/plot1D_evolution.py
hans/cli/plot1D_height.py
hans/cli/plot1D_last.py
hans/cli/plot2D_height.py
hans/cli/plot2D_last.py
hans/cli/plot_scalar.py
hans/cli/read_config.py
hans/models/__init__.py
hans/models/density.py
hans/models/pressure.py
hans/models/sound_speed.py
hans/models/velocity_profile.py
hans/models/viscosity.py
hans/models/viscous_stress_newton.py
hans/models/viscous_stress_powerlaw.py
hans/multiscale/__init__.py
hans/multiscale/db.py
hans/multiscale/gp.py
hans/multiscale/md.py
hans/multiscale/util.py
hans/special/__init__.py
hans/special/flux_limiter.py
hans-0.3.2.dist-info/entry_points.txt
hans-0.3.2.dist-info/licenses/LICENSE.md
hans-0.3.2.dist-info/WHEEL
hans-0.3.2.dist-info/METADATA
hans-0.3.2.dist-info/RECORD
