Metadata-Version: 2.4
Name: hans
Version: 0.3.2
Summary: Height-Averaged Navier-Stokes (HANS) solver for 2D lubrication problems
Author-email: Hannes Holey <hannes.holey@kit.edu>
Requires-Python: >=3.9, <3.13
Classifier: Programming Language :: Python :: 3
Classifier: License :: OSI Approved :: MIT License
License-File: LICENSE.md
Requires-Dist: matplotlib>=3.2.0
Requires-Dist: numpy>=1.22.4, <2.0.0
Requires-Dist: netCDF4>=1.5.3
Requires-Dist: PyYAML>=5.3
Requires-Dist: mpi4py>=3.0
Requires-Dist: scipy>=1.12
Requires-Dist: GPy==1.13.2
Requires-Dist: dtool
Requires-Dist: dtool-lookup-api==0.5.1
Requires-Dist: sphinx ; extra == "doc"
Requires-Dist: sphinx_rtd_theme ; extra == "doc"
Requires-Dist: myst-nb ; extra == "doc"
Requires-Dist: jupytext ; extra == "doc"
Requires-Dist: sympy ; extra == "doc"
Requires-Dist: lammps ; extra == "multiscale"
Requires-Dist: pytest ; extra == "test"
Requires-Dist: coverage>=5.0.3 ; extra == "test"
Project-URL: Source, https://github.com/hannes-holey/hans
Provides-Extra: doc
Provides-Extra: multiscale
Provides-Extra: test
